ebbbe_start.py
setup.py
ebbbe/__init__.py
ebbbe/version.py
ebbbe.egg-info/PKG-INFO
ebbbe.egg-info/SOURCES.txt
ebbbe.egg-info/dependency_links.txt
ebbbe.egg-info/requires.txt
ebbbe.egg-info/top_level.txt
ebbbe/cpu/__init__.py
ebbbe/cpu/alu.py
ebbbe/cpu/bus.py
ebbbe/cpu/clock.py
ebbbe/cpu/cpu.py
ebbbe/cpu/cu.py
ebbbe/cpu/ram.py
ebbbe/cpu/reg.py
ebbbe/view/__init__.py
ebbbe/view/constants.py
ebbbe/view/dialog_about.py
ebbbe/view/dialog_memory.py
ebbbe/view/settings.py
ebbbe/view/ui.py
ebbbe/view/utils.py
ebbbe/view/widget_bus.py
ebbbe/view/widget_clock.py
ebbbe/view/widget_dip.py
ebbbe/view/widget_flags.py
ebbbe/view/widget_ir.py
ebbbe/view/widget_led.py
ebbbe/view/widget_led_bank.py
ebbbe/view/widget_mar.py
ebbbe/view/widget_out.py
ebbbe/view/widget_pc.py
ebbbe/view/widget_ram.py
ebbbe/view/widget_reg.py
ebbbe/view/widget_seq.py
ebbbe/view/window_main.py
ebbbe/view/res/__init__.py
ebbbe/view/res/__init__.pyc
ebbbe/view/res/about.ui
ebbbe/view/res/dialog_memory.ui
ebbbe/view/res/widget_bus.ui
ebbbe/view/res/widget_clock.ui
ebbbe/view/res/widget_flags.ui
ebbbe/view/res/widget_ir.ui
ebbbe/view/res/widget_mar.ui
ebbbe/view/res/widget_out.ui
ebbbe/view/res/widget_pc.ui
ebbbe/view/res/widget_ram.ui
ebbbe/view/res/widget_reg.ui
ebbbe/view/res/widget_seq.ui
ebbbe/view/res/window_main.ui