Metadata-Version: 1.1
Name: ebbbe
Version: 0.2.0
Summary: An emulation of of Ben Eater's 8-bit breadboard computer (https://eater.net/8bit/)
Home-page: https://eartoearoak.com/software/ebbbe
Author: Al Brown
Author-email: al [at] eartoearok.com
License: GPLv2
Keywords: 8-bit breadboard computer emulator
Platform: UNKNOWN
Classifier: Development Status :: 4 - Beta
Classifier: License :: OSI Approved :: GNU General Public License v2 (GPLv2)
Classifier: Operating System :: MacOS :: MacOS X
Classifier: Operating System :: Microsoft :: Windows
Classifier: Operating System :: POSIX :: Linux
Classifier: Programming Language :: Python :: 2.7
Classifier: Topic :: Education
Classifier: Topic :: System :: Emulators
